definitions.vh
`ifndef DEFINITIONS_VH
`define DEFINITIONS_VH

// Width definitions
`define DATA_WIDTH 32   // Data width in bits
`define ADDR_WIDTH 32   // Address width in bits
`define INST_WIDTH 32
`define NUM_REGISTER 32

// Memory size
//`define MEM_SIZE (1 << `ADDR_WIDTH) // Total number of memory locations

`define FUNCT_7 7

// RISC-V Base Instruction Set Opcodes
`define OPCODE 7
`define OP_LUI     7'b0110111 // Load Upper Immediate
`define OP_AUIPC   7'b0010111 // Add Upper Immediate to PC
`define OP_JAL     7'b1101111 // Jump and Link
`define OP_JALR    7'b1100111 // Jump and Link Register
`define OP_BRANCH  7'b1100011 // Branch Instructions (BEQ, BNE, BLT, etc.)
`define OP_LOAD    7'b0000011 // Load Instructions (LB, LH, LW, LBU, LHU)
`define OP_STORE   7'b0100011 // Store Instructions (SB, SH, SW)
`define OP_ALU     7'b0110011 // ALU Instructions (ADD, SUB, AND, OR, XOR, etc.)
`define OP_ALUI    7'b0010011 // ALU Immediate Instructions (ADDI, ANDI, ORI, XORI, etc.)
`define OP_FENCE   7'b0001111 // Fence
`define OP_SYSTEM  7'b1110011 // System Instructions (ECALL, EBREAK, etc.)

// RISC-V ALU Operations
`define OP_ALU_NOP    6'b000000 
`define OP_ALU_ADD    6'b011001 // Add
`define OP_ALU_SUB    6'b011011 // Subtract
`define OP_ALU_AND    6'b011101 // Bitwise AND
`define OP_ALU_OR     6'b011111 // Bitwise OR
`define OP_ALU_XOR    6'b100001 // Bitwise XOR
`define OP_ALU_SLT    6'b100011 // Set Less Than (signed)
`define OP_ALU_SLTU   6'b100101 // Set Less Than (unsigned)
`define OP_ALU_SLL    6'b100111 // Shift Left Logical
`define OP_ALU_SRL    6'b101001 // Shift Right Logical
`define OP_ALU_SRA    6'b101011 // Shift Right Arithmetic

`define BRANCH_BEQ    3'b000 // Branch Equal
`define BRANCH_BNE    3'b001 // Branch Not Equal
`define BRANCH_BLT    3'b100 // Branch Less Than
`define BRANCH_BGE    3'b101 // Branch Greater Than Or Equal
`define BRANCH_BLTU    3'b110 // Branch Less Than Unsigned
`define BRANCH_BGEU    3'b111 // Branch Greater Than Or Equal Unsigned

`define BRANCH_JAL_JALR 3'b010

// Other constants or parameters can be defined here

`endif

RTLdesign/branch.v
`include "../definitions.vh"

module branch_unit (
    input wire i_branch,
    input wire [2:0] i_branch_op,
    input wire [`DATA_WIDTH-1:0] i_a,
    input wire [`DATA_WIDTH-1:0] i_b,
    output reg o_take
);
    always @* begin
        o_take = 0;
        if(i_branch) begin
            case (i_branch_op)
                `BRANCH_BEQ: begin //BEQ
                    if(i_a == i_b) begin 
                        o_take = 1;
                    end
                end 
                `BRANCH_BNE : begin //BNE
                    if(i_a != i_b) begin 
                        o_take = 1;
                    end
                end 
                `BRANCH_BLT: begin //BLT
                    if($signed(i_a) < $signed(i_b)) begin 
                        o_take = 1;
                    end
                end 
                `BRANCH_BGE: begin //BGE
                    if($signed(i_a) >= $signed(i_b)) begin 
                        o_take = 1;
                    end
                end 
                `BRANCH_BLTU: begin //BLTU
                    if(i_a < i_b) begin 
                        o_take = 1;
                    end    
                end
                `BRANCH_BGEU: begin //BGEU
                    if(i_a >= i_b) begin 
                        o_take = 1;
                    end
                end 
                `BRANCH_JAL_JALR: begin 
                    o_take = 1;
                end
                default: o_take = 0; 
            endcase
        end
    end
endmodule

testbench/branch_tb.v
`include "../RTLdesign/branch.v"
`default_nettype none
`timescale 1ns/1ns

`define assert(signal, value) \
        if (signal !== value) begin \
            $display("ASSERTION FAILED at %2d in %m: signal != value", $time); \
            $finish; \
        end

module  branch_unit_tb;

  reg clk;
  reg i_branch = 1'b0;
  reg [2:0] i_branch_op = 3'b000;
  reg [`DATA_WIDTH-1:0] i_a = 32'h00000000;
  reg [`DATA_WIDTH-1:0] i_b = 32'h00000000;
  
  wire o_take;

  branch_unit dut (
    .i_branch(i_branch),
    .i_branch_op(i_branch_op),
    .i_a(i_a),
    .i_b(i_b),
    .o_take(o_take)
  );
  
  initial begin
    clk = 1'b0;
  end

  always #5 clk = ~clk;

  initial begin
      i_a = 32'h00000000;
      i_b = 32'h00000000;
      i_branch = 1'b1;
      i_branch_op = `BRANCH_BEQ;
    #10;
      `assert(dut.o_take, 1'b1);
      i_branch = 1'b1;
      i_branch_op = `BRANCH_BNE;
    #10;
      `assert(dut.o_take, 1'b0);
      i_branch = 1'b1;
      i_branch_op = `BRANCH_BNE;
      i_a = 32'h00000000;
      i_b = 32'h00000001;
    #10;
      `assert(dut.o_take, 1'b1);
      //-1
      i_a = 32'h11111111;
      //-2
      i_b = 32'h11111110;
      i_branch = 1'b1;
      i_branch_op = `BRANCH_BLT;
    #10;
      `assert(dut.o_take, 1'b0);
      i_branch = 1'b1;
      i_branch_op = `BRANCH_BGE;  
    #10;
      `assert(dut.o_take, 1'b1);
      i_branch = 1'b1;
      i_branch_op = `BRANCH_BLTU;  
    #10;
      `assert(dut.o_take, 1'b0);
      i_branch = 1'b1;
      i_branch_op = `BRANCH_BGEU; 
    #10;
      `assert(dut.o_take, 1'b1);
      i_branch = 1'b1;
      i_branch_op = `BRANCH_JAL_JALR;  
    #10;
      `assert(dut.o_take, 1'b1);
      i_branch = 1'b0;
      i_branch_op = `BRANCH_JAL_JALR;  
    #10;
      `assert(dut.o_take, 1'b0);
    $finish;

  end

  always @(posedge clk) begin 
    $display("time %2t, i_branch = %b, i_branch_op = %3b, i_a = %8h, i_b = %8h, o_take = %b", $time, i_branch, i_branch_op, i_a, i_b, o_take);
  end 
  
  initial begin
    $dumpfile("branch_unit.vcd");
    $dumpvars;  
  end

endmodule

waveforms/branch_unit.vcd
$date
	Fri Jul 18 16:58:57 2025
$end
$version
	Icarus Verilog
$end
$timescale
	1ns
$end
$scope module branch_unit_tb $end
$var wire 1 ! o_take $end
$var reg 1 " clk $end
$var reg 32 # i_a [31:0] $end
$var reg 32 $ i_b [31:0] $end
$var reg 1 % i_branch $end
$var reg 3 & i_branch_op [2:0] $end
$scope module dut $end
$var wire 32 ' i_a [31:0] $end
$var wire 32 ( i_b [31:0] $end
$var wire 1 % i_branch $end
$var wire 3 ) i_branch_op [2:0] $end
$var reg 1 ! o_take $end
$upscope $end
$upscope $end
$enddefinitions $end
$comment Show the parameter values. $end
$dumpall
$end
#0
$dumpvars
b0 )
b0 (
b0 '
b0 &
1%
b0 $
b0 #
0"
1!
$end
#5
1"
#10
0!
0"
b1 &
b1 )
#15
1"
#20
1!
0"
b1 $
b1 (
#25
1"
#30
0!
0"
b100 &
b100 )
b10001000100010001000100010000 $
b10001000100010001000100010000 (
b10001000100010001000100010001 #
b10001000100010001000100010001 '
#35
1"
#40
1!
0"
b101 &
b101 )
#45
1"
#50
0!
0"
b110 &
b110 )
#55
1"
#60
1!
0"
b111 &
b111 )
#65
1"
#70
1!
0"
b10 &
b10 )
#75
1"
#80
0!
0"
0%
